tensora/__init__.py
tensora/_stable_set.py
tensora/cli.py
tensora/codegen/__init__.py
tensora/codegen/_hoist_declarations.py
tensora/codegen/_ir_to_c.py
tensora/codegen/_ir_to_llvm.py
tensora/codegen/_type_to_c.py
tensora/codegen/_type_to_llvm.py
tensora/compile/__init__.py
tensora/compile/_cffi_ownership.py
tensora/compile/_compile_cffi.py
tensora/compile/_compile_llvm.py
tensora/compile/_initialize_llvm.py
tensora/compile/_porcelain.py
tensora/compile/_tensor_method.py
tensora/desugar/__init__.py
tensora/desugar/_best_algorithm.py
tensora/desugar/_desugar_expression.py
tensora/desugar/_exceptions.py
tensora/desugar/_index_dimensions.py
tensora/desugar/_to_identifiable.py
tensora/desugar/_to_iteration_graphs.py
tensora/desugar/ast.py
tensora/expression/__init__.py
tensora/expression/_exceptions.py
tensora/expression/_parser.py
tensora/expression/ast.py
tensora/format/__init__.py
tensora/format/_exceptions.py
tensora/format/_format.py
tensora/format/_parser.py
tensora/generate/__init__.py
tensora/generate/_base.py
tensora/generate/_deparse_to_taco.py
tensora/generate/_tensora.py
tensora/ir/__init__.py
tensora/ir/_builder.py
tensora/ir/_peephole.py
tensora/ir/ast.py
tensora/ir/types.py
tensora/iteration_graph/__init__.py
tensora/iteration_graph/_definition.py
tensora/iteration_graph/_generate_ir.py
tensora/iteration_graph/_names.py
tensora/iteration_graph/_write_sparse_ir.py
tensora/iteration_graph/identifiable_expression/__init__.py
tensora/iteration_graph/identifiable_expression/_exhaust_tensor.py
tensora/iteration_graph/identifiable_expression/_extract_context.py
tensora/iteration_graph/identifiable_expression/_tensor_layer.py
tensora/iteration_graph/identifiable_expression/_to_ir.py
tensora/iteration_graph/identifiable_expression/ast.py
tensora/iteration_graph/iteration_graph.py
tensora/iteration_graph/outputs/__init__.py
tensora/iteration_graph/outputs/_append.py
tensora/iteration_graph/outputs/_base.py
tensora/iteration_graph/outputs/_bucket.py
tensora-0.5.0.dist-info/WHEEL
tensora-0.5.0.dist-info/entry_points.txt
tensora-0.5.0.dist-info/METADATA
tensora-0.5.0.dist-info/RECORD
