Metadata-Version: 2.4
Name: tensora
Version: 0.5.0
Summary: Library for dense and sparse tensors built on the tensor algebra compiler
Keywords: tensor,sparse,matrix,array
Author: David Hagen
Author-email: David Hagen <david@drhagen.com>
License-Expression: MIT
Classifier: Development Status :: 4 - Beta
Classifier: Intended Audience :: Science/Research
Classifier: Intended Audience :: Developers
Classifier: License :: OSI Approved :: MIT License
Classifier: Operating System :: POSIX :: Linux
Classifier: Operating System :: MacOS :: MacOS X
Classifier: Operating System :: Microsoft :: Windows
Classifier: Programming Language :: Python :: 3
Classifier: Programming Language :: Python :: 3.10
Classifier: Programming Language :: Python :: 3.11
Classifier: Programming Language :: Python :: 3.12
Classifier: Programming Language :: Python :: 3.13
Classifier: Programming Language :: Python :: 3.14
Classifier: Topic :: Software Development :: Libraries :: Python Modules
Requires-Dist: returns>=0.20,<0.27
Requires-Dist: cffi~=1.16
Requires-Dist: llvmlite==0.46.*
Requires-Dist: parsita==2.*
Requires-Dist: typer==0.21.*
Requires-Dist: setuptools>=69 ; python_full_version >= '3.12' and extra == 'cffi'
Requires-Dist: numpy>=1.24,<3.0 ; extra == 'numpy'
Requires-Dist: scipy~=1.7 ; extra == 'scipy'
Requires-Python: >=3.10
Project-URL: Documentation, https://tensora.drhagen.com
Project-URL: Repository, https://github.com/drhagen/tensora
Provides-Extra: cffi
Provides-Extra: numpy
Provides-Extra: scipy
